MANIFEST.in
README.md
setup.py
cddd/__init__.py
cddd/evaluation.py
cddd/hyperparameters.py
cddd/inference.py
cddd/input_pipeline.py
cddd/model_helper.py
cddd/models.py
cddd/preprocessing.py
cddd/run_cddd.py
cddd/train.py
cddd.egg-info/PKG-INFO
cddd.egg-info/SOURCES.txt
cddd.egg-info/dependency_links.txt
cddd.egg-info/entry_points.txt
cddd.egg-info/requires.txt
cddd.egg-info/top_level.txt
cddd/data/__init__.py
cddd/data/download_pretrained.py
cddd/data/inchi_dict1.npy
cddd/data/inchi_dict2.npy
cddd/data/indices_char.npy
cddd/data/indices_char_2.npy