Metadata-Version: 2.1
Name: cddd
Version: 1.2.3
Summary: continous and data-driven molecular descriptors (CDDD)
Home-page: https://github.com/jrwnter/cddd
Author: Robin Winter
Author-email: robin.winter@bayer.com
License: MIT
Download-URL: https://github.com/jrwnter/cddd/archive/refs/tags/1.2.3.tar.gz
Platform: UNKNOWN
Requires-Python: >=3.6.1, <3.7
Provides-Extra: cpu
